Metadata-Version: 2.3
Name: aurelis-cli
Version: 1.0.0
Summary: Enterprise-grade CLI-based AI code assistant powered by GitHub Models
License: MIT
Keywords: ai,code-assistant,cli,enterprise,code-analysis,github-models
Author: Gamecooler19
Author-email: pradyumn.tandon@kanopus.org
Maintainer: Kanopus Development Team
Maintainer-email: support@kanopus.org
Requires-Python: >=3.10
Classifier: Development Status :: 5 - Production/Stable
Classifier: Intended Audience :: Developers
Classifier: License :: OSI Approved :: MIT License
Classifier: Operating System :: OS Independent
Classifier: Programming Language :: Python :: 3
Classifier: Programming Language :: Python :: 3.10
Classifier: Programming Language :: Python :: 3.11
Classifier: Programming Language :: Python :: 3.12
Classifier: Topic :: Software Development :: Code Generators
Classifier: Topic :: Software Development :: Quality Assurance
Classifier: Topic :: Software Development :: Libraries :: Python Modules
Requires-Dist: PyYAML (>=6.0.1)
Requires-Dist: aiofiles (>=23.2.0)
Requires-Dist: aiohttp (>=3.9.1)
Requires-Dist: alembic (>=1.13.1)
Requires-Dist: azure-ai-inference (>=1.0.0b4)
Requires-Dist: azure-core (>=1.29.0)
Requires-Dist: click (>=8.1.7)
Requires-Dist: cryptography (>=41.0.7)
Requires-Dist: gitpython (>=3.1.40)
Requires-Dist: jinja2 (>=3.1.0)
Requires-Dist: packaging (>=23.0)
Requires-Dist: prompt-toolkit (>=3.0.0)
Requires-Dist: psutil (>=5.9.6)
Requires-Dist: pydantic (>=2.5.0)
Requires-Dist: pygments (>=2.17.2)
Requires-Dist: python-dotenv (>=1.0.0)
Requires-Dist: requests (>=2.31.0)
Requires-Dist: rich (>=13.7.0)
Requires-Dist: sqlalchemy (>=2.0.25)
Requires-Dist: typer (>=0.9.0,<0.10.0)
Requires-Dist: watchdog (>=3.0.0)
Project-URL: Changelog, https://github.com/kanopusdev/aurelis/blob/main/CHANGELOG.md
Project-URL: Documentation, https://aurelis.kanopus.org/docs
Project-URL: Homepage, https://aurelis.kanopus.org
Project-URL: Issues, https://github.com/kanopusdev/aurelis/issues
Project-URL: Repository, https://github.com/kanopusdev/aurelis
